Linkedin/seven segment decoder/seven_segment.v
module seven_segment(
    input  [3:0] bcd,
    output reg [6:0] seg
);

always @(*) begin
    case(bcd)
        4'b0000: seg = 7'b1111110; // 0
        4'b0001: seg = 7'b0110000; // 1
        4'b0010: seg = 7'b1101101; // 2
        4'b0011: seg = 7'b1111001; // 3
        4'b0100: seg = 7'b0110011; // 4
        4'b0101: seg = 7'b1011011; // 5
        4'b0110: seg = 7'b1011111; // 6
        4'b0111: seg = 7'b1110000; // 7
        4'b1000: seg = 7'b1111111; // 8
        4'b1001: seg = 7'b1111011; // 9
        default: seg = 7'b0000000; // OFF
    endcase
end
endmodule

Linkedin/seven segment decoder/seven_segment_tb.v
module seven_segemnt_tb;

reg  [3:0] bcd;
wire [6:0] seg;

seven_segment uut (
    .bcd(bcd),
    .seg(seg)
);

initial begin
    $dumpfile("seven_segment.vcd");
    $dumpvars(0, seven_segemnt_tb);

    bcd = 4'b0000; #10;
    bcd = 4'b0001; #10;
    bcd = 4'b0010; #10;
    bcd = 4'b0011; #10;
    bcd = 4'b0100; #10;
    bcd = 4'b0101; #10;
    bcd = 4'b0110; #10;
    bcd = 4'b0111; #10;
    bcd = 4'b1000; #10;
    bcd = 4'b1001; #10;

    $finish;
end

endmodule

Linkedin/seven segment decoder/seven_segment.vcd
$date
	Sun Feb 22 23:46:00 2026
$end
$version
	Icarus Verilog
$end
$timescale
	1s
$end
$scope module seven_segemnt_tb $end
$var wire 7 ! seg [6:0] $end
$var reg 4 " bcd [3:0] $end
$scope module uut $end
$var wire 4 # bcd [3:0] $end
$var reg 7 $ seg [6:0] $end
$upscope $end
$upscope $end
$enddefinitions $end
$comment Show the parameter values. $end
$dumpall
$end
#0
$dumpvars
b1111110 $
b0 #
b0 "
b1111110 !
$end
#10
b110000 !
b110000 $
b1 "
b1 #
#20
b1101101 !
b1101101 $
b10 "
b10 #
#30
b1111001 !
b1111001 $
b11 "
b11 #
#40
b110011 !
b110011 $
b100 "
b100 #
#50
b1011011 !
b1011011 $
b101 "
b101 #
#60
b1011111 !
b1011111 $
b110 "
b110 #
#70
b1110000 !
b1110000 $
b111 "
b111 #
#80
b1111111 !
b1111111 $
b1000 "
b1000 #
#90
b1111011 !
b1111011 $
b1001 "
b1001 #
