Linkedin/bintogray/bintogray.v
module bintogray(
    input  wire [3:0] b,
    output wire [3:0] g
);
    assign g[3] = b[3];
    assign g[2] = b[3] ^ b[2];
    assign g[1] = b[2] ^ b[1];
    assign g[0] = b[1] ^ b[0];

endmodule

Linkedin/bintogray/bin2gray_tb.v
`timescale 1ns/1ps
module bin2gray_tb;
    reg  [3:0] b;
    wire [3:0] g;
    bintogray dut (.b(b),.g(g) );
    initial begin
        $dumpfile("bin2gray.vcd");
        $dumpvars(0, bin2gray_tb);
        b = 4'b0000; #10;   //0 
        b = 4'b0001; #10;   //1 
        b = 4'b0010; #10;   //2
        b = 4'b0011; #10;   //3
        b = 4'b0100; #10;   //4
        b = 4'b0101; #10;   //5
        b = 4'b0110; #10;   //6
        b = 4'b0111; #10;   //7
        b = 4'b1000; #10;   //8
        b=  4'b1001;#10 ;   //9
        b =4'b1010; #10;    //10-A
        b=4'b1011; #10;     //11-B
        b=4'b1100;#10;      //12-C
        b=4'b1101; #10;     //13-D
        b=4'b1110; #10;     //14-E
        b=4'b1111; #10;     //15-F

        $finish;
    end

endmodule

Linkedin/bintogray/bin2gray.vcd
$date
	Sun Feb 22 11:09:09 2026
$end
$version
	Icarus Verilog
$end
$timescale
	1ps
$end
$scope module bin2gray_tb $end
$var wire 4 ! g [3:0] $end
$var reg 4 " b [3:0] $end
$scope module dut $end
$var wire 4 # b [3:0] $end
$var wire 4 $ g [3:0] $end
$upscope $end
$upscope $end
$enddefinitions $end
$comment Show the parameter values. $end
$dumpall
$end
#0
$dumpvars
b0 $
b0 #
b0 "
b0 !
$end
#10000
b1 !
b1 $
b1 "
b1 #
#20000
b11 !
b11 $
b10 "
b10 #
#30000
b10 !
b10 $
b11 "
b11 #
#40000
b110 !
b110 $
b100 "
b100 #
#50000
b111 !
b111 $
b101 "
b101 #
#60000
b101 !
b101 $
b110 "
b110 #
#70000
b100 !
b100 $
b111 "
b111 #
#80000
b1100 !
b1100 $
b1000 "
b1000 #
#90000
b1101 !
b1101 $
b1001 "
b1001 #
#100000
b1111 !
b1111 $
b1010 "
b1010 #
#110000
b1110 !
b1110 $
b1011 "
b1011 #
#120000
b1010 !
b1010 $
b1100 "
b1100 #
#130000
b1011 !
b1011 $
b1101 "
b1101 #
#140000
b1001 !
b1001 $
b1110 "
b1110 #
#150000
b1000 !
b1000 $
b1111 "
b1111 #
